mmcif_utils/__init__.py
mmcif_utils/bird/PdbxBirdIndex.py
mmcif_utils/bird/PdbxFamilyIo.py
mmcif_utils/bird/PdbxPrd.py
mmcif_utils/bird/PdbxPrdCcIo.py
mmcif_utils/bird/PdbxPrdIo.py
mmcif_utils/bird/PdbxPrdUtils.py
mmcif_utils/bird/__init__.py
mmcif_utils/bird/cl/PdbxPrdExec.py
mmcif_utils/bird/cl/__init__.py
mmcif_utils/chemcomp/PdbxChemComp.py
mmcif_utils/chemcomp/PdbxChemCompIo.py
mmcif_utils/chemcomp/PdbxChemCompModel.py
mmcif_utils/chemcomp/PdbxChemCompModelIo.py
mmcif_utils/chemcomp/PdbxChemCompUtils.py
mmcif_utils/chemcomp/__init__.py
mmcif_utils/inventory/InventoryIo.py
mmcif_utils/inventory/InventoryIoBatchRunner.py
mmcif_utils/inventory/__init__.py
mmcif_utils/message/PdbxMessage.py
mmcif_utils/message/PdbxMessageIo.py
mmcif_utils/message/__init__.py
mmcif_utils/pdb/PdbxAnnFeature.py
mmcif_utils/pdb/PdbxAtomSite.py
mmcif_utils/pdb/PdbxConnect.py
mmcif_utils/pdb/PdbxConnectTests.py
mmcif_utils/pdb/PdbxVersion.py
mmcif_utils/pdb/__init__.py
mmcif_utils/pdbx/PdbxIo.py
mmcif_utils/pdbx/__init__.py
mmcif_utils/persist/LockFile.py
mmcif_utils/persist/PdbxCoreIoAdapter.py
mmcif_utils/persist/PdbxDictionaryInfo.py
mmcif_utils/persist/PdbxPersist.py
mmcif_utils/persist/PdbxPyIoAdapter.py
mmcif_utils/persist/__init__.py
mmcif_utils/style/ChemCompCategoryStyle.py
mmcif_utils/style/ChemCompCategoryStyleWithOutStndAtom.py
mmcif_utils/style/ChemCompModelCategoryStyle.py
mmcif_utils/style/PdbxCategoryStyleBase.py
mmcif_utils/style/PdbxEmExtensionCategoryStyle.py
mmcif_utils/style/PdbxEntryInfoCategoryStyle.py
mmcif_utils/style/PdbxGeometryReportCategoryStyle.py
mmcif_utils/style/PdbxItemMappingCategoryStyle.py
mmcif_utils/style/PdbxLocalMapIndexCategoryStyle.py
mmcif_utils/style/PdbxMessageCategoryStyle.py
mmcif_utils/style/PdbxReportCategoryStyle.py
mmcif_utils/style/PdbxStatusHistoryCategoryStyle.py
mmcif_utils/style/PdbxStyleIoUtil.py
mmcif_utils/style/PdbxXrayExpReportCategoryStyle.py
mmcif_utils/style/PrdCategoryStyle.py
mmcif_utils/style/__init__.py
mmcif_utils-0.32.dist-info/licenses/LICENSE
mmcif_utils-0.32.dist-info/METADATA
mmcif_utils-0.32.dist-info/WHEEL
mmcif_utils-0.32.dist-info/top_level.txt
mmcif_utils-0.32.dist-info/zip-safe
mmcif_utils-0.32.dist-info/RECORD
